PyLinkedList2905/PyLinkedList2905.py
PyLinkedList2905/__init__.py
PyLinkedList2905-0.1.7.dist-info/LICENSE
PyLinkedList2905-0.1.7.dist-info/METADATA
PyLinkedList2905-0.1.7.dist-info/WHEEL
PyLinkedList2905-0.1.7.dist-info/top_level.txt
PyLinkedList2905-0.1.7.dist-info/RECORD
