Metadata-Version: 2.1
Name: PyLinkedList2905
Version: 0.1.7
Summary: A simple linked list implementation in Python
Home-page: https://github.com/Nouments/linked_list
Author: RAKOTONIRINA Manankasina Nomentsoa
Author-email: nomentsua@gmail.com
Classifier: Programming Language :: Python :: 3
Classifier: License :: OSI Approved :: MIT License
Classifier: Operating System :: OS Independent
Requires-Python: >=3.6
License-File: LICENSE
